__init__.py
gmmvi/__init__.py
gmmvi/gmmvi_runner.py
gmmvi/configs/__init__.py
gmmvi/configs/experiment_configs/breast_cancer.yml
gmmvi/configs/experiment_configs/breast_cancer_mb.yml
gmmvi/configs/experiment_configs/german_credit.yml
gmmvi/configs/experiment_configs/german_credit_mb.yml
gmmvi/configs/experiment_configs/gmm100.yml
gmmvi/configs/experiment_configs/gmm20.yml
gmmvi/configs/experiment_configs/planar_robot_4.yml
gmmvi/configs/experiment_configs/stm20.yml
gmmvi/configs/experiment_configs/stm300.yml
gmmvi/configs/experiment_configs/talos.yml
gmmvi/configs/experiment_configs/wine.yml
gmmvi/configs/module_configs/component_adaptation/adaptive.yml
gmmvi/configs/module_configs/component_adaptation/fixed.yml
gmmvi/configs/module_configs/component_stepsize_adaptation/decaying.yml
gmmvi/configs/module_configs/component_stepsize_adaptation/fixed.yml
gmmvi/configs/module_configs/component_stepsize_adaptation/improvement-based.yml
gmmvi/configs/module_configs/ng_based_component_updater/direct.yml
gmmvi/configs/module_configs/ng_based_component_updater/iBLR.yml
gmmvi/configs/module_configs/ng_based_component_updater/trust-region.yml
gmmvi/configs/module_configs/ng_estimator/MORE.yml
gmmvi/configs/module_configs/ng_estimator/Stein.yml
gmmvi/configs/module_configs/sample_selector/component-based.yml
gmmvi/configs/module_configs/sample_selector/mixture-based.yml
gmmvi/configs/module_configs/weight_stepsize_adaptation/decaying.yml
gmmvi/configs/module_configs/weight_stepsize_adaptation/fixed.yml
gmmvi/configs/module_configs/weight_stepsize_adaptation/improvement-based.yml
gmmvi/configs/module_configs/weight_updater/direct.yml
gmmvi/configs/module_configs/weight_updater/trust-region.yml
gmmvi/experiments/__init__.py
gmmvi/experiments/setup_experiment.py
gmmvi/experiments/evaluation/__init__.py
gmmvi/experiments/evaluation/mmd.py
gmmvi/experiments/evaluation/visualize_planar_robot.py
gmmvi/experiments/target_distributions/__init__.py
gmmvi-1.1.dist-info/LICENSE
gmmvi-1.1.dist-info/METADATA
gmmvi-1.1.dist-info/WHEEL
gmmvi-1.1.dist-info/top_level.txt
gmmvi-1.1.dist-info/RECORD
